ezedcfg/__init__.py
ezedcfg/ezedcfg.py
ezedcfg-0.1.7.dist-info/DESCRIPTION.rst
ezedcfg-0.1.7.dist-info/METADATA
ezedcfg-0.1.7.dist-info/RECORD
ezedcfg-0.1.7.dist-info/WHEEL
ezedcfg-0.1.7.dist-info/metadata.json
ezedcfg-0.1.7.dist-info/top_level.txt
