Metadata-Version: 2.0
Name: ezedcfg
Version: 0.1.7
Summary: A basic configuration loading package
Home-page: https://github.com/stephenflynn/ezedcfg
Author: Stephen Flynn
Author-email: dev@stephenflynn.net
License: MIT license
Keywords: ezedcfg
Platform: UNKNOWN
Classifier: Development Status :: 2 - Pre-Alpha
Classifier: Intended Audience :: Developers
Classifier: License :: OSI Approved :: MIT License
Classifier: Natural Language :: English
Classifier: Programming Language :: Python :: 3.4
Classifier: Programming Language :: Python :: 3.5
Classifier: Programming Language :: Python :: 3.6
Requires-Dist: PyYAML
